asdf_astropy/__init__.py
asdf_astropy/_version.py
asdf_astropy/conftest.py
asdf_astropy/exceptions.py
asdf_astropy/extensions.py
asdf_astropy/integration.py
asdf_astropy/converters/__init__.py
asdf_astropy/converters/helpers.py
asdf_astropy/converters/utils.py
asdf_astropy/converters/coordinates/__init__.py
asdf_astropy/converters/coordinates/angle.py
asdf_astropy/converters/coordinates/earth_location.py
asdf_astropy/converters/coordinates/frame.py
asdf_astropy/converters/coordinates/representation.py
asdf_astropy/converters/coordinates/sky_coord.py
asdf_astropy/converters/coordinates/spectral_coord.py
asdf_astropy/converters/coordinates/tests/__init__.py
asdf_astropy/converters/coordinates/tests/test_angle.py
asdf_astropy/converters/coordinates/tests/test_earth_location.py
asdf_astropy/converters/coordinates/tests/test_frame.py
asdf_astropy/converters/coordinates/tests/test_masked.py
asdf_astropy/converters/coordinates/tests/test_representation.py
asdf_astropy/converters/coordinates/tests/test_sky_coord.py
asdf_astropy/converters/coordinates/tests/test_spectral_coord.py
asdf_astropy/converters/fits/__init__.py
asdf_astropy/converters/fits/fits.py
asdf_astropy/converters/fits/tests/__init__.py
asdf_astropy/converters/fits/tests/test_fits.py
asdf_astropy/converters/nddata/__init__.py
asdf_astropy/converters/nddata/uncertainty.py
asdf_astropy/converters/nddata/tests/__init__.py
asdf_astropy/converters/nddata/tests/test_uncertainty.py
asdf_astropy/converters/table/__init__.py
asdf_astropy/converters/table/table.py
asdf_astropy/converters/table/tests/__init__.py
asdf_astropy/converters/table/tests/test_table.py
asdf_astropy/converters/time/__init__.py
asdf_astropy/converters/time/time.py
asdf_astropy/converters/time/time_delta.py
asdf_astropy/converters/time/tests/__init__.py
asdf_astropy/converters/time/tests/test_time.py
asdf_astropy/converters/time/tests/test_time_delta.py
asdf_astropy/converters/transform/__init__.py
asdf_astropy/converters/transform/compound.py
asdf_astropy-0.9.0.dist-info/licenses/LICENSE.rst
asdf_astropy-0.9.0.dist-info/METADATA
asdf_astropy-0.9.0.dist-info/WHEEL
asdf_astropy-0.9.0.dist-info/entry_points.txt
asdf_astropy-0.9.0.dist-info/top_level.txt
asdf_astropy-0.9.0.dist-info/RECORD
