Metadata-Version: 2.4
Name: asdf-astropy
Version: 0.9.0
Summary: ASDF serialization support for astropy
Author-email: The Astropy Developers <astropy.team@gmail.com>
Project-URL: documentation, https://asdf-astropy.readthedocs.io/en/latest/
Project-URL: repository, https://github.com/astropy/asdf-astropy
Project-URL: tracker, https://github.com/astropy/asdf-astropy/issues
Classifier: Development Status :: 5 - Production/Stable
Classifier: Programming Language :: Python
Classifier: Programming Language :: Python :: 3
Requires-Python: >=3.11
License-File: LICENSE.rst
Requires-Dist: asdf>=3.3.0
Requires-Dist: asdf-coordinates-schemas>=0.4
Requires-Dist: asdf-transform-schemas>=0.6
Requires-Dist: asdf-standard>=1.1.0
Requires-Dist: astropy>=5.3.0
Requires-Dist: numpy>=1.26
Requires-Dist: packaging>=19
Provides-Extra: docs
Requires-Dist: docutils; extra == "docs"
Requires-Dist: graphviz; extra == "docs"
Requires-Dist: matplotlib; extra == "docs"
Requires-Dist: sphinx; extra == "docs"
Requires-Dist: sphinx-asdf; extra == "docs"
Requires-Dist: sphinx-astropy; extra == "docs"
Requires-Dist: sphinx-automodapi; extra == "docs"
Requires-Dist: tomli; extra == "docs"
Provides-Extra: test
Requires-Dist: coverage; extra == "test"
Requires-Dist: pytest-astropy; extra == "test"
Requires-Dist: pytest-asdf-plugin; extra == "test"
Requires-Dist: pytest; extra == "test"
Requires-Dist: scipy; extra == "test"
Dynamic: license-file
